bigbeans.py
deserializers.py
bigbeans-0.0.6.dist-info/WHEEL
bigbeans-0.0.6.dist-info/METADATA
bigbeans-0.0.6.dist-info/NOTICE
bigbeans-0.0.6.dist-info/README
bigbeans-0.0.6.dist-info/RECORD
