Metadata-Version: 2.1
Name: bigbeans
Author: AI Depot LLC
Author-email: feedback@lnti.me
Home-page: https://www.bigbeans.ai/
License: Apache 2.0
Summary: BigBeans Client
Project-URL: Documentation, https://www.bigbeans.ai/docs
Classifier: Development Status :: 3 - Alpha
Classifier: Intended Audience :: Developers
Classifier: Intended Audience :: Education
Classifier: Intended Audience :: Science/Research
Classifier: License :: OSI Approved :: Apache Software License
Classifier: Programming Language :: Python :: 3
Classifier: Topic :: Scientific/Engineering
Classifier: Topic :: Scientific/Engineering :: Mathematics
Classifier: Topic :: Scientific/Engineering :: Artificial Intelligence
Classifier: Topic :: Software Development
Classifier: Topic :: Software Development :: Libraries
Classifier: Topic :: Software Development :: Libraries :: Python Modules
Requires-Dist: pandas
Requires-Dist: requests
Requires-Dist: numpy
Version: 0.0.6
